Workbook

Sheet Checklist Lanzamiento
A1: ESTETICAI — CHECKLIST DE LANZAMIENTO
A2: Plan completo para pasar de MVP a producto comercializable (59-249 EUR/mes)
A4: PROGRESO GLOBAL | C4: =CONCATENATE(ROUND(COUNTIF(C8:C200,"Hecho")/COUNTA(C8:C200)*100,0),"%") -> 24% | D4: =COUNTIF(C8:C200,"Hecho")&"/"&COUNTA(C8:C200) -> 16/68
A6: # | B6: TAREA | C6: ESTADO | D6: PRIORIDAD | E6: NOTAS / DETALLE | F6: RESPONSABLE
A8: PRODUCTO — Funcionalidades Core
A9: 1 | B9: Registro + login de clientas | C9: Hecho | D9: P0 | E9: Funciona con email + password. Falta: recuperar contraseña | F9: Dev
A10: 2 | B10: Perfil de marca completo | C10: Hecho | D10: P0 | E10: Nombre, servicios, productos, tono, valores, redes, horarios | F10: Dev
A11: 3 | B11: Generador de copy individual | C11: Hecho | D11: P0 | E11: Con contexto completo de marca, validación JSON, botón copiar | F11: Dev
A12: 4 | B12: Generador de calendario semanal | C12: Hecho | D12: P0 | E12: 6 publicaciones lun-sáb, estrategia semanal, consejo | F12: Dev
A13: 5 | B13: Generador de imágenes con IA | C13: Hecho | D13: P0 | E13: Flux Pro v1.1 via fal.ai. Requiere FAL_KEY con saldo | F13: Dev
A14: 6 | B14: Generador de video (imagen→Reel) | C14: Hecho | D14: P1 | E14: Kling v2 Master via fal.ai. 7 tipos de movimiento | F14: Dev
A15: 7 | B15: Mejora de foto real (fondo+calidad) | C15: Hecho | D15: P1 | E15: BiRefNet + Bria + Crystal Upscaler. Pipeline 3 pasos | F15: Dev
A16: 8 | B16: Composición Antes/Después | C16: Hecho | D16: P0 | E16: 4 plantillas Pillow, coste cero, <1 segundo | F16: Dev
A17: 9 | B17: Base de conocimiento estética (26 servicios) | C17: Hecho | D17: P1 | E17: Info técnica real para copies más creíbles | F17: Dev
A18: 10 | B18: Historial de generaciones | C18: Hecho | D18: P2 | E18: Últimas 20 generaciones en dashboard. Sin detalle expandido | F18: Dev
A19: PRODUCTO — Funcionalidades Faltantes
A20: 1 | B20: Recuperar contraseña (forgot password) | C20: Pendiente | D20: P1 | E20: Necesita servicio de email (SendGrid, Resend, etc.) | F20: Dev
A21: 2 | B21: Editar perfil existente | C21: Pendiente | D21: P1 | E21: Solo se puede crear nuevo, no editar el actual | F21: Dev
A22: 3 | B22: Descarga directa de imágenes generadas | C22: Pendiente | D22: P1 | E22: Ahora solo se ve en navegador. Falta botón descargar | F22: Dev
A23: 4 | B23: Galería/historial con previews | C23: Pendiente | D23: P2 | E23: El historial actual es muy básico, sin previsualizaciones | F23: Dev
A24: 5 | B24: Multi-perfil (varios negocios) | C24: Pendiente | D24: P3 | E24: Una clienta puede tener varias marcas. Ahora solo 1 activo | F24: Dev
A25: 6 | B25: Regenerar / pedir variaciones | C25: Pendiente | D25: P2 | E25: Botón 'No me convence, genera otro' en cada resultado | F25: Dev
A26: 7 | B26: Exportar calendario a PDF o imagen | C26: Pendiente | D26: P2 | E26: Para que la clienta lo imprima o envíe a su equipo | F26: Dev
A27: 8 | B27: Tutorial / onboarding primera vez | C27: Pendiente | D27: P1 | E27: Guía paso a paso la primera vez que entra al dashboard | F27: Dev
A28: INFRAESTRUCTURA Y TÉCNICO
A29: 1 | B29: Deploy en Railway funcionando | C29: Hecho | D29: P0 | E29: Auto-deploy desde GitHub. URL pública activa | F29: Dev
A30: 2 | B30: Base de datos persistente (SQLite /data) | C30: Hecho | D30: P0 | E30: Volumen de 400MB en Railway | F30: Dev
A31: 3 | B31: HTTPS activo | C31: Hecho | D31: P0 | E31: Railway lo proporciona automáticamente | F31: Dev
A32: 4 | B32: Variables de entorno configuradas | C32: Hecho | D32: P0 | E32: ANTHROPIC_API_KEY, FAL_KEY, SECRET_KEY en Railway | F32: Dev
A33: 5 | B33: Dominio propio (esteticai.com o similar) | C33: Pendiente | D33: P1 | E33: Ahora usa URL de Railway. Necesita dominio profesional | F33: Marta
A34: 6 | B34: Migrar de SQLite a PostgreSQL | C34: Pendiente | D34: P2 | E34: SQLite vale para <100 clientas. Para escalar, Postgres | F34: Dev
A35: 7 | B35: Backups automáticos de base de datos | C35: Pendiente | D35: P1 | E35: Si se pierde el volumen, se pierden todas las clientas | F35: Dev
A36: 8 | B36: Monitoring y alertas (uptime) | C36: Pendiente | D36: P2 | E36: Saber si la app se cae. UptimeRobot (gratis) o similar | F36: Dev
A37: 9 | B37: Rate limiting en endpoints API | C37: Pendiente | D37: P2 | E37: Evitar que alguien genere 1000 imágenes en un minuto | F37: Dev
A38: 10 | B38: Logs centralizados | C38: Pendiente | D38: P3 | E38: Railway tiene logs básicos. Para debug en producción | F38: Dev
A39: SEGURIDAD
A40: 1 | B40: Hash de passwords (SHA256) | C40: Hecho | D40: P0 | E40: Funciona pero sin salt. Migrar a bcrypt antes de escalar | F40: Dev
A41: 2 | B41: Migrar a bcrypt o argon2 | C41: Pendiente | D41: P1 | E41: SHA256 sin salt es vulnerable a rainbow tables | F41: Dev
A42: 3 | B42: CSRF protection | C42: Pendiente | D42: P2 | E42: FastAPI + SessionMiddleware no tiene CSRF por defecto | F42: Dev
A43: 4 | B43: Validación de inputs en servidor | C43: Parcial | D43: P1 | E43: Validamos tamaño foto. Falta: sanitizar texto, SQL injection | F43: Dev
A44: 5 | B44: API keys NO expuestas en frontend | C44: Hecho | D44: P0 | E44: Todas las API calls son server-side | F44: Dev
A45: 6 | B45: Política de privacidad y cookies | C45: Pendiente | D45: P0 | E45: Obligatorio por RGPD para operar en España/UE | F45: Marta
A46: 7 | B46: Aviso legal / condiciones de uso | C46: Pendiente | D46: P0 | E46: Obligatorio si se cobra por el servicio | F46: Marta
A47: 8 | B47: Consentimiento de datos (RGPD) | C47: Pendiente | D47: P0 | E47: Checkbox en registro + política accesible | F47: Dev + Marta
A48: MODELO DE NEGOCIO
A49: 1 | B49: Definir planes y precios finales | C49: Parcial | D49: P0 | E49: Idea: 59/99/249 EUR. Falta definir qué incluye cada plan | F49: Marta
A50: 2 | B50: Pasarela de pago (Stripe) | C50: Pendiente | D50: P0 | E50: Sin pago no hay negocio. Stripe es lo estándar en Europa | F50: Dev
A51: 3 | B51: Sistema de planes (free/basic/pro) | C51: Pendiente | D51: P0 | E51: Limitar generaciones por plan. Ej: Free=5, Basic=50, Pro=∞ | F51: Dev
A52: 4 | B52: Control de uso por clienta | C52: Pendiente | D52: P1 | E52: Contador de generaciones mensuales + avisos de límite | F52: Dev
A53: 5 | B53: Página de precios pública | C53: Pendiente | D53: P0 | E53: Sección en el landing que muestre los planes | F53: Dev
A54: 6 | B54: Facturación automática | C54: Pendiente | D54: P1 | E54: Stripe Billing o Stripe Invoicing para facturas | F54: Dev
A55: 7 | B55: Período de prueba gratuito | C55: Pendiente | D55: P1 | E55: 7-14 días de prueba sin tarjeta, o con tarjeta sin cobro | F55: Marta
A56: 8 | B56: Email de bienvenida automático | C56: Pendiente | D56: P2 | E56: Cuando se registra una clienta, mail con guía rápida | F56: Dev
A57: 9 | B57: Coste operativo por clienta estimado | C57: Pendiente | D57: P0 | E57: Calcular coste API por uso medio: fal.ai + Anthropic | F57: Marta + Dev
A58: LEGAL Y COMPLIANCE
A59: 1 | B59: Registro como autónoma o SL | C59: Pendiente | D59: P0 | E59: Necesario para cobrar legalmente en España | F59: Marta
A60: 2 | B60: Política de privacidad (RGPD) | C60: Pendiente | D60: P0 | E60: Datos que se recogen, para qué, y derechos del usuario | F60: Marta
A61: 3 | B61: Aviso legal con datos fiscales | C61: Pendiente | D61: P0 | E61: Obligatorio en web comercial española | F61: Marta
A62: 4 | B62: Condiciones de contratación | C62: Pendiente | D62: P0 | E62: Qué se contrata, duración, cancelación, reembolsos | F62: Marta
A63: 5 | B63: Política de cookies | C63: Pendiente | D63: P1 | E63: Banner de cookies si se usa analytics | F63: Dev
A64: 6 | B64: Alta en AEPD (tratamiento de datos) | C64: Pendiente | D64: P1 | E64: Registro de actividades de tratamiento | F64: Marta
A65: 7 | B65: Seguro de responsabilidad civil | C65: Pendiente | D65: P3 | E65: Opcional pero recomendable para SaaS B2B | F65: Marta
A66: MARKETING Y VENTAS
A67: 1 | B67: Landing page optimizada para conversión | C67: Parcial | D67: P0 | E67: Existe pero falta: testimonios, demos, precio, FAQ | F67: Dev
A68: 2 | B68: Demo en video (Loom o similar) | C68: Pendiente | D68: P0 | E68: Video de 2 min mostrando el producto en acción | F68: Marta
A69: 3 | B69: Captación de leads (formulario interés) | C69: Pendiente | D69: P1 | E69: Antes de cobrar: recoger emails de interesadas | F69: Dev
A70: 4 | B70: Redes sociales propias de Esteticai | C70: Pendiente | D70: P1 | E70: Instagram @esteticai con contenido de ejemplo | F70: Marta
A71: 5 | B71: Contenido de ejemplo (portfolio) | C71: Pendiente | D71: P0 | E71: 3-5 ejemplos reales de calendarios, copies, imágenes | F71: Marta
A72: 6 | B72: 3-5 beta testers reales | C72: Pendiente | D72: P0 | E72: Clientas reales probando 2 semanas gratis | F72: Marta
A73: 7 | B73: Recoger feedback de beta testers | C73: Pendiente | D73: P1 | E73: Formulario o entrevista después de probar | F73: Marta
A74: 8 | B74: Propuesta de valor en 1 frase | C74: Pendiente | D74: P0 | E74: Ej: 'Tu community manager IA por 59€/mes' | F74: Marta
A75: 9 | B75: Comparativa con competidores en web | C75: Pendiente | D75: P2 | E75: Tabla visual mostrando ventajas vs Predis.ai, etc. | F75: Dev
A76: 10 | B76: Canal de adquisición definido | C76: Pendiente | D76: P1 | E76: Instagram Ads, boca a boca, referidos, ferias de estética... | F76: Marta
A77: SOPORTE Y OPERACIONES
A78: 1 | B78: Email de soporte configurado | C78: Pendiente | D78: P1 | E78: soporte@esteticai.com o similar | F78: Marta
A79: 2 | B79: FAQ / Centro de ayuda | C79: Pendiente | D79: P2 | E79: Preguntas frecuentes en la web | F79: Marta + Dev
A80: 3 | B80: Chat de soporte en la app | C80: Pendiente | D80: P3 | E80: Crisp, Intercom o WhatsApp Business. Para después | F80: Dev
A81: 4 | B81: Proceso de onboarding de nueva clienta | C81: Pendiente | D81: P1 | E81: ¿Se dan de alta solas o les ayudamos? ¿Llamada inicial? | F81: Marta
A82: 5 | B82: SLA definido (tiempo de respuesta) | C82: Pendiente | D82: P2 | E82: Ej: respondemos en <24h laborables | F82: Marta
A83: 6 | B83: Documentación interna del producto | C83: Pendiente | D83: P3 | E83: Para que otros devs puedan mantener el código | F83: Dev

Sheet Resumen por Area
A1: RESUMEN POR AREA
A3: Area | B3: Hechos | C3: Pendientes | D3: Parciales | E3: % Completado
A4: Producto — Core | B4: =COUNTIF('Checklist Lanzamiento'!C8:C18,"Hecho") -> 10 | C4: =COUNTIF('Checklist Lanzamiento'!C8:C18,"Pendiente") -> 0 | D4: =COUNTIF('Checklist Lanzamiento'!C8:C18,"Parcial") -> 0 | E4: =IF(COUNTA('Checklist Lanzamiento'!C8:C18)>0,ROUND(COUNTIF('Checklist Lanzamiento'!C8:C18,"Hecho")/COUNTA('Checklist Lanzamiento'!C8:C18)*100,0)&"%","—") -> 100%
A5: Producto — Faltantes | B5: =COUNTIF('Checklist Lanzamiento'!C19:C27,"Hecho") -> 0 | C5: =COUNTIF('Checklist Lanzamiento'!C19:C27,"Pendiente") -> 8 | D5: =COUNTIF('Checklist Lanzamiento'!C19:C27,"Parcial") -> 0 | E5: =IF(COUNTA('Checklist Lanzamiento'!C19:C27)>0,ROUND(COUNTIF('Checklist Lanzamiento'!C19:C27,"Hecho")/COUNTA('Checklist Lanzamiento'!C19:C27)*100,0)&"%","—") -> 0%
A6: Infraestructura | B6: =COUNTIF('Checklist Lanzamiento'!C29:C38,"Hecho") -> 4 | C6: =COUNTIF('Checklist Lanzamiento'!C29:C38,"Pendiente") -> 6 | D6: =COUNTIF('Checklist Lanzamiento'!C29:C38,"Parcial") -> 0 | E6: =IF(COUNTA('Checklist Lanzamiento'!C29:C38)>0,ROUND(COUNTIF('Checklist Lanzamiento'!C29:C38,"Hecho")/COUNTA('Checklist Lanzamiento'!C29:C38)*100,0)&"%","—") -> 40%
A7: Seguridad | B7: =COUNTIF('Checklist Lanzamiento'!C40:C48,"Hecho") -> 2 | C7: =COUNTIF('Checklist Lanzamiento'!C40:C48,"Pendiente") -> 5 | D7: =COUNTIF('Checklist Lanzamiento'!C40:C48,"Parcial") -> 1 | E7: =IF(COUNTA('Checklist Lanzamiento'!C40:C48)>0,ROUND(COUNTIF('Checklist Lanzamiento'!C40:C48,"Hecho")/COUNTA('Checklist Lanzamiento'!C40:C48)*100,0)&"%","—") -> 25%
A8: Modelo de negocio | B8: =COUNTIF('Checklist Lanzamiento'!C50:C58,"Hecho") -> 0 | C8: =COUNTIF('Checklist Lanzamiento'!C50:C58,"Pendiente") -> 8 | D8: =COUNTIF('Checklist Lanzamiento'!C50:C58,"Parcial") -> 0 | E8: =IF(COUNTA('Checklist Lanzamiento'!C50:C58)>0,ROUND(COUNTIF('Checklist Lanzamiento'!C50:C58,"Hecho")/COUNTA('Checklist Lanzamiento'!C50:C58)*100,0)&"%","—") -> 0%
A9: Legal | B9: =COUNTIF('Checklist Lanzamiento'!C60:C66,"Hecho") -> 0 | C9: =COUNTIF('Checklist Lanzamiento'!C60:C66,"Pendiente") -> 6 | D9: =COUNTIF('Checklist Lanzamiento'!C60:C66,"Parcial") -> 0 | E9: =IF(COUNTA('Checklist Lanzamiento'!C60:C66)>0,ROUND(COUNTIF('Checklist Lanzamiento'!C60:C66,"Hecho")/COUNTA('Checklist Lanzamiento'!C60:C66)*100,0)&"%","—") -> 0%
A10: Marketing y ventas | B10: =COUNTIF('Checklist Lanzamiento'!C68:C77,"Hecho") -> 0 | C10: =COUNTIF('Checklist Lanzamiento'!C68:C77,"Pendiente") -> 9 | D10: =COUNTIF('Checklist Lanzamiento'!C68:C77,"Parcial") -> 0 | E10: =IF(COUNTA('Checklist Lanzamiento'!C68:C77)>0,ROUND(COUNTIF('Checklist Lanzamiento'!C68:C77,"Hecho")/COUNTA('Checklist Lanzamiento'!C68:C77)*100,0)&"%","—") -> 0%
A11: Soporte | B11: =COUNTIF('Checklist Lanzamiento'!C79:C84,"Hecho") -> 0 | C11: =COUNTIF('Checklist Lanzamiento'!C79:C84,"Pendiente") -> 5 | D11: =COUNTIF('Checklist Lanzamiento'!C79:C84,"Parcial") -> 0 | E11: =IF(COUNTA('Checklist Lanzamiento'!C79:C84)>0,ROUND(COUNTIF('Checklist Lanzamiento'!C79:C84,"Hecho")/COUNTA('Checklist Lanzamiento'!C79:C84)*100,0)&"%","—") -> 0%
A12: TOTAL | B12: =SUM(B4:B11) -> 16 | C12: =SUM(C4:C11) -> 47 | D12: =SUM(D4:D11) -> 1 | E12: =IF((B12+C12+D12)>0,ROUND(B12/(B12+C12+D12)*100,0)&"%","—") -> 25%

Sheet Roadmap
A1: ROADMAP DE LANZAMIENTO
A3: TAREA | B3: DETALLE | C3: RESPONSABLE | D3: TIEMPO EST.
A4: FASE 1: DEMO (1 semana)
A5: Ya completado | B5: App funcional con 6 herramientas, deploy en Railway | C5: Dev | D5: Hecho
A6: Ya completado | B6: UI pulida, tildes, spinner, fallbacks visuales | C6: Dev | D6: Hecho
A7: Dominio propio | B7: Registrar esteticai.com/.es y conectar a Railway | C7: Marta | D7: 2 horas
A8: Contenido ejemplo | B8: Crear 3-5 ejemplos reales de calendarios e imágenes | C8: Marta | D8: 1 día
A9: Video demo | B9: Grabar pantalla mostrando el flujo completo (Loom) | C9: Marta | D9: 2 horas
A10: FASE 2: BETA (2-3 semanas)
A11: Beta testers | B11: Conseguir 3-5 esteticistas reales para probar gratis | C11: Marta | D11: 1 semana
A12: Editar perfil | B12: Permitir modificar el perfil de marca sin crear uno nuevo | C12: Dev | D12: 3 horas
A13: Onboarding | B13: Tutorial guiado la primera vez que entra al dashboard | C13: Dev | D13: 1 día
A14: Recuperar password | B14: Flujo de 'olvidé mi contraseña' con email | C14: Dev | D14: 4 horas
A15: Descargar imágenes | B15: Botón descargar en todas las imágenes generadas | C15: Dev | D15: 2 horas
A16: Feedback beta | B16: Recoger opiniones y ajustar producto | C16: Marta | D16: Continuo
A17: FASE 3: MONETIZACIÓN (2-4 semanas)
A18: Textos legales | B18: Privacidad, aviso legal, condiciones (abogado o plantilla) | C18: Marta | D18: 1 semana
A19: RGPD | B19: Checkbox consentimiento en registro + banner cookies | C19: Dev + Marta | D19: 1 día
A20: Stripe integración | B20: Pasarela de pago con 3 planes | C20: Dev | D20: 3-5 días
A21: Planes y límites | B21: Sistema que controla generaciones por plan | C21: Dev | D21: 2 días
A22: Página de precios | B22: Sección en landing con planes, precios y CTA | C22: Dev | D22: 4 horas
A23: Prueba gratuita | B23: 14 días sin tarjeta para nuevas clientas | C23: Dev | D23: 3 horas
A24: FASE 4: LANZAMIENTO (1-2 semanas)
A25: Backups DB | B25: Script automático de backup diario | C25: Dev | D25: 3 horas
A26: Bcrypt passwords | B26: Migrar hashing de SHA256 a bcrypt | C26: Dev | D26: 2 horas
A27: Monitoring | B27: UptimeRobot o similar para alertas de caída | C27: Dev | D27: 1 hora
A28: Landing optimizada | B28: Testimonios de beta, demos, FAQ, social proof | C28: Dev + Marta | D28: 2 días
A29: Redes de Esteticai | B29: Perfil de Instagram con contenido de muestra | C29: Marta | D29: 1 semana
A30: Lanzamiento | B30: Abrir registro público, activar cobros, anunciar | C30: Marta | D30: 1 día
